hyperliquid_mcp/__init__.py
hyperliquid_mcp/server.py
mcp_hyperliquid-0.1.0.dist-info/METADATA
mcp_hyperliquid-0.1.0.dist-info/WHEEL
mcp_hyperliquid-0.1.0.dist-info/entry_points.txt
mcp_hyperliquid-0.1.0.dist-info/licenses/LICENSE
mcp_hyperliquid-0.1.0.dist-info/RECORD
