Metadata-Version: 2.4
Name: mcp-hyperliquid
Version: 0.1.0
Summary: Model Context Protocol server for Hyperliquid trading using the official Python SDK
Project-URL: Homepage, https://github.com/edkdev/hyperliquid-mcp
Project-URL: Repository, https://github.com/edkdev/hyperliquid-mcp
Project-URL: Issues, https://github.com/edkdev/hyperliquid-mcp/issues
Project-URL: Documentation, https://github.com/edkdev/hyperliquid-mcp#readme
Author-email: Ed <edkdev@proton.me>
License: MIT
License-File: LICENSE
Keywords: ai,assistant,hyperliquid,mcp,model-context-protocol,trading
Classifier: Development Status :: 4 - Beta
Classifier: Intended Audience :: Developers
Classifier: License :: OSI Approved :: MIT License
Classifier: Programming Language :: Python :: 3
Classifier: Programming Language :: Python :: 3.10
Classifier: Programming Language :: Python :: 3.11
Classifier: Programming Language :: Python :: 3.12
Classifier: Topic :: Office/Business :: Financial :: Investment
Classifier: Topic :: Software Development :: Libraries :: Python Modules
Requires-Python: >=3.10
Requires-Dist: hyperliquid-python-sdk>=0.6.0
Requires-Dist: mcp>=1.0.0
Provides-Extra: dev
Requires-Dist: black>=23.0.0; extra == 'dev'
Requires-Dist: mypy>=1.0.0; extra == 'dev'
Requires-Dist: pytest>=7.0.0; extra == 'dev'
